hu_city.py
hu_city-1.0.0.dist-info/METADATA
hu_city-1.0.0.dist-info/WHEEL
hu_city-1.0.0.dist-info/top_level.txt
hu_city-1.0.0.dist-info/RECORD
