Metadata-Version: 2.1
Name: hu_city
Version: 1.0.0
Summary: Hungarian city names
Home-page: https://github.com/kobanya/hu_city
Author: Nagy Béla
Author-email: nagy.belabudapest@gmail.com
Classifier: Programming Language :: Python :: 3
Classifier: License :: OSI Approved :: MIT License
Classifier: Operating System :: OS Independent
